callgg/__init__.py
callgg/__main__.py
callgg-1.0.3.dist-info/entry_points.txt
callgg-1.0.3.dist-info/LICENSE
callgg-1.0.3.dist-info/WHEEL
callgg-1.0.3.dist-info/METADATA
callgg-1.0.3.dist-info/RECORD
