Metadata-Version: 2.1
Name: callgg
Version: 1.0.3
Summary: GGUF caller
Author-email: calcuis <info@calcu.io>
Classifier: License :: OSI Approved :: MIT License
Requires-Dist: gguf-selector
Project-URL: Homepage, https://github.com/calcuis/callgg
Project-URL: Issues, https://github.com/calcuis/callgg/issues
